__init__.py
apidevtools/__init__.py
apidevtools/logman.py
apidevtools/utils.py
apidevtools/media/ARIALNB.TTF
apidevtools/media/__init__.py
apidevtools/media/imgproc.py
apidevtools/media/telegraph.py
apidevtools/orm/__init__.py
apidevtools/orm/mysql.py
apidevtools/orm/postgresql.py
apidevtools/orm/sqlite.py
apidevtools/orm/types/__init__.py
apidevtools/orm/types/_connector.py
apidevtools/orm/types/types.py
apidevtools/orm/types/_operations/__init__.py
apidevtools/orm/types/_operations/_operation.py
apidevtools/orm/types/_operations/delete.py
apidevtools/orm/types/_operations/insert.py
apidevtools/orm/types/_operations/select.py
apidevtools/orm/types/_operations/update.py
apidevtools/security/__init__.py
apidevtools/security/encryptor.py
apidevtools/security/hasher.py
apidevtools/simpleorm/__init__.py
apidevtools/simpleorm/orm.py
apidevtools/simpleorm/redis.py
apidevtools/simpleorm/connectors/__init__.py
apidevtools/simpleorm/connectors/_connector.py
apidevtools/simpleorm/connectors/mysql.py
apidevtools/simpleorm/connectors/postgresql.py
apidevtools/simpleorm/connectors/sqlite.py
apidevtools/simpleorm/types/__init__.py
apidevtools/simpleorm/types/records.py
apidevtools/simpleorm/types/schema.py
apidevtools-4.0.5.dist-info/LICENSE.txt
apidevtools-4.0.5.dist-info/METADATA
apidevtools-4.0.5.dist-info/WHEEL
apidevtools-4.0.5.dist-info/top_level.txt
apidevtools-4.0.5.dist-info/RECORD
