Metadata-Version: 2.1
Name: apidevtools
Version: 4.0.5
Summary: All in one tools for API development.
Author-email: cxllmerichie <cxllmerichie@gmail.com>
Maintainer-email: cxllmerichie <cxllmerichie@gmail.com>
License: MIT License
Project-URL: Homepage, https://github.com/cxllmerichie/apidevtools
Project-URL: Bug Tracker, https://github.com/cxllmerichie/apidevtools/issues
Project-URL: Repository, https://github.com/cxllmerichie/apidevtools
Project-URL: Documentation, https://github.com/cxllmerichie/apidevtools/README.md
Classifier: Topic :: Software Development :: Libraries :: Python Modules
Classifier: Topic :: Security :: Cryptography
Classifier: Topic :: Database :: Front-Ends
Classifier: Programming Language :: Python :: Implementation :: CPython
Classifier: Programming Language :: Python :: 3.10
Classifier: Natural Language :: English
Classifier: Development Status :: 4 - Beta
Classifier: Framework :: FastAPI
Classifier: Intended Audience :: Developers
Classifier: Operating System :: OS Independent
Classifier: License :: OSI Approved :: MIT License
Requires-Python: >=3.10
License-File: LICENSE.txt
Provides-Extra: compressed
Requires-Dist: lz4 ; extra == 'compressed'
Provides-Extra: encryptor
Requires-Dist: cryptography ; extra == 'encryptor'
Provides-Extra: hasher
Requires-Dist: argon2-cffi ; extra == 'hasher'
Provides-Extra: imgproc
Requires-Dist: pillow ; extra == 'imgproc'
Requires-Dist: numpy ; extra == 'imgproc'
Provides-Extra: mysql
Requires-Dist: aiomysql ; extra == 'mysql'
Requires-Dist: loguru ; extra == 'mysql'
Provides-Extra: orm
Requires-Dist: loguru ; extra == 'orm'
Requires-Dist: pydantic ; extra == 'orm'
Provides-Extra: postgresql
Requires-Dist: asyncpg ; extra == 'postgresql'
Requires-Dist: loguru ; extra == 'postgresql'
Provides-Extra: redis
Requires-Dist: aioredis ; extra == 'redis'
Provides-Extra: speedup
Requires-Dist: cchardet ; extra == 'speedup'
Provides-Extra: sqlite
Requires-Dist: aiosqlite ; extra == 'sqlite'
Requires-Dist: loguru ; extra == 'sqlite'
Provides-Extra: telegraph
Requires-Dist: aiohttp ; extra == 'telegraph'
Requires-Dist: aiodns ; extra == 'telegraph'
Requires-Dist: ujson ; extra == 'telegraph'
